setup.py
opticspy/__init__.py
opticspy/aperture.py
opticspy/asphere.py
opticspy/diffraction.py
opticspy/gauss.py
opticspy/interferometer_seidel.py
opticspy/interferometer_zenike.py
opticspy/jones.py
opticspy/phaseunwrap.py
opticspy/seidel.py
opticspy/seidel2.py
opticspy/tools.py
opticspy/zernike.py
opticspy/zernike_rec.py
opticspy.egg-info/PKG-INFO
opticspy.egg-info/SOURCES.txt
opticspy.egg-info/dependency_links.txt
opticspy.egg-info/requires.txt
opticspy.egg-info/top_level.txt
opticspy/lens/__init__.py
opticspy/lens/aberration.py
opticspy/lens/zoom_position.py
opticspy/mplot3d/__init__.py
opticspy/mplot3d/art3d.py
opticspy/mplot3d/axes3d.py
opticspy/mplot3d/axis3d.py
opticspy/mplot3d/proj3d.py
opticspy/test/__init__.py
opticspy/test/test_surface.py
opticspy/test/test_surface2.py