Metadata-Version: 1.0
Name: opticspy
Version: 0.1.2
Summary: Python optics module
Home-page: http://opticspy.org
Author: Xing Fan
Author-email: marvin.fanxing@gmail.com
License: MIT License
Keywords: optic,lens,zernike
Platform: UNKNOWN
